CONTRIBUTING.rst
LICENSE
MANIFEST.in
README.rst
setup.py
docs/Makefile
docs/make.bat
docs/source/chart-classes.rst
docs/source/conf.py
docs/source/examples-of-chart-types.rst
docs/source/index.rst
docs/source/introduction.rst
docs/source/resources.rst
docs/source/classes-doc/NVD3Chart.rst
docs/source/classes-doc/cumulative-line-chart.rst
docs/source/classes-doc/discrete-bar-chart.rst
docs/source/classes-doc/line-chart.rst
docs/source/classes-doc/line-plus-bar-chart.rst
docs/source/classes-doc/line-with-focus-chart.rst
docs/source/classes-doc/multi-bar-chart.rst
docs/source/classes-doc/multi-bar-horizontal-chart.rst
docs/source/classes-doc/pie-chart.rst
docs/source/classes-doc/scatter-chart.rst
docs/source/classes-doc/stacked-area-chart.rst
nvd3/NVD3Chart.py
nvd3/__init__.py
nvd3/cumulativeLineChart.py
nvd3/discreteBarChart.py
nvd3/ipynb.py
nvd3/lineChart.py
nvd3/linePlusBarChart.py
nvd3/lineWithFocusChart.py
nvd3/multiBarChart.py
nvd3/multiBarHorizontalChart.py
nvd3/pieChart.py
nvd3/scatterChart.py
nvd3/stackedAreaChart.py
nvd3/translator.py
nvd3/templates/base.html
nvd3/templates/content.html
nvd3/templates/cumulativelinechart.html
nvd3/templates/discretebarchart.html
nvd3/templates/linebarwfocuschart.html
nvd3/templates/linechart.html
nvd3/templates/lineplusbarchart.html
nvd3/templates/linewfocuschart.html
nvd3/templates/multibarchart.html
nvd3/templates/multibarcharthorizontal.html
nvd3/templates/page.html
nvd3/templates/piechart.html
nvd3/templates/scatterchart.html
nvd3/templates/stackedareachart.html
python_nvd3.egg-info/PKG-INFO
python_nvd3.egg-info/SOURCES.txt
python_nvd3.egg-info/dependency_links.txt
python_nvd3.egg-info/entry_points.txt
python_nvd3.egg-info/namespace_packages.txt
python_nvd3.egg-info/not-zip-safe
python_nvd3.egg-info/requires.txt
python_nvd3.egg-info/top_level.txt