Metadata-Version: 1.1
Name: python-nvd3
Version: 0.14.1
Summary: Python NVD3 - Chart Library for d3.js
Home-page: http://github.com/areski/python-nvd3
Author: Belaid Arezqui
Author-email: areski@gmail.com
License: MIT
Keywords: plot,graph,nvd3,d3
Platform: UNKNOWN
Classifier: Development Status :: 5 - Production/Stable
Classifier: Environment :: Console
Classifier: Intended Audience :: Developers
Classifier: License :: OSI Approved :: MIT License
Classifier: Operating System :: OS Independent
Classifier: Programming Language :: Python
Classifier: Programming Language :: Python :: 2
Classifier: Programming Language :: Python :: 2.7
Classifier: Programming Language :: Python :: 3
Classifier: Programming Language :: Python :: 3.3
Classifier: Programming Language :: Python :: 3.4
Classifier: Programming Language :: Python :: 3.5
Classifier: Topic :: Multimedia :: Graphics :: Presentation
Classifier: Topic :: Software Development :: Libraries :: Python Modules
